LICENSE
MANIFEST.in
README.rst
setup.cfg
setup.py
djangocms_rest_api/__init__.py
djangocms_rest_api/settings.py
djangocms_rest_api/urls.py
djangocms_rest_api.egg-info/PKG-INFO
djangocms_rest_api.egg-info/SOURCES.txt
djangocms_rest_api.egg-info/dependency_links.txt
djangocms_rest_api.egg-info/requires.txt
djangocms_rest_api.egg-info/top_level.txt
djangocms_rest_api/serializers/__init__.py
djangocms_rest_api/serializers/base.py
djangocms_rest_api/serializers/filerimageplugin_serializer.py
djangocms_rest_api/serializers/mapping.py
djangocms_rest_api/serializers/utils.py
djangocms_rest_api/views/__init__.py
djangocms_rest_api/views/base.py
djangocms_rest_api/views/utils.py