Metadata-Version: 1.1
Name: djangocms-rest-api
Version: 0.2.0
Summary: API for django cms.
Home-page: https://github.com/divio/djangocms-rest-api
Author: SteelKiwi Development, Divio
Author-email: getmansky@steelkiwi.com
License: MIT
Keywords: djangocms-rest-api
Platform: UNKNOWN
Classifier: Development Status :: 2 - Pre-Alpha
Classifier: Framework :: Django
Classifier: Framework :: Django :: 1.8
Classifier: Framework :: Django :: 1.9
Classifier: Intended Audience :: Developers
Classifier: License :: OSI Approved :: MIT License
Classifier: Natural Language :: English
Classifier: Programming Language :: Python :: 2
Classifier: Programming Language :: Python :: 2.7
Classifier: Programming Language :: Python :: 3
Classifier: Programming Language :: Python :: 3.4
Classifier: Programming Language :: Python :: 3.5
